openai_responses/__init__.py
openai_responses/_api.py
openai_responses/_constants/__init__.py
openai_responses/_constants/system_models.py
openai_responses/_mock.py
openai_responses/_routes/__init__.py
openai_responses/_routes/_base.py
openai_responses/_routes/beta/__init__.py
openai_responses/_routes/beta/assistants.py
openai_responses/_routes/beta/chat.py
openai_responses/_routes/beta/messages.py
openai_responses/_routes/beta/run_steps.py
openai_responses/_routes/beta/runs.py
openai_responses/_routes/beta/threads.py
openai_responses/_routes/beta/vector_store_file_batches.py
openai_responses/_routes/beta/vector_store_files.py
openai_responses/_routes/beta/vector_stores.py
openai_responses/_routes/chat.py
openai_responses/_routes/embeddings.py
openai_responses/_routes/files.py
openai_responses/_routes/models.py
openai_responses/_routes/moderation.py
openai_responses/_types/generics.py
openai_responses/_types/partials/assistants.py
openai_responses/_types/partials/chat.py
openai_responses/_types/partials/deleted.py
openai_responses/_types/partials/embeddings.py
openai_responses/_types/partials/files.py
openai_responses/_types/partials/messages.py
openai_responses/_types/partials/models.py
openai_responses/_types/partials/moderation.py
openai_responses/_types/partials/run_steps.py
openai_responses/_types/partials/runs.py
openai_responses/_types/partials/sync_cursor_page.py
openai_responses/_types/partials/threads.py
openai_responses/_types/partials/vector_store_file_batches.py
openai_responses/_types/partials/vector_store_files.py
openai_responses/_types/partials/vector_stores.py
openai_responses/_utils/aio.py
openai_responses/_utils/copy.py
openai_responses/_utils/faker.py
openai_responses/_utils/serde.py
openai_responses/_utils/time.py
openai_responses/ext/__init__.py
openai_responses/ext/httpx.py
openai_responses/ext/respx.py
openai_responses/helpers/builders/_base.py
openai_responses/helpers/builders/assistants.py
openai_responses/helpers/builders/chat.py
openai_responses-0.12.0.dist-info/LICENSE
openai_responses-0.12.0.dist-info/METADATA
openai_responses-0.12.0.dist-info/WHEEL
openai_responses-0.12.0.dist-info/entry_points.txt
openai_responses-0.12.0.dist-info/RECORD
