Metadata-Version: 2.1
Name: openai-responses
Version: 0.12.0
Summary: 🧪🤖 Pytest plugin for automatically mocking OpenAI requests
Home-page: https://mharrisb1.github.io/openai-responses-python/
License: MIT
Keywords: openai,pytest,testing
Author: Michael Harris
Author-email: mharris@definite.app
Requires-Python: >=3.9,<4.0
Classifier: License :: OSI Approved :: MIT License
Classifier: Programming Language :: Python :: 3
Classifier: Programming Language :: Python :: 3.9
Classifier: Programming Language :: Python :: 3.10
Classifier: Programming Language :: Python :: 3.11
Classifier: Programming Language :: Python :: 3.12
Classifier: Topic :: Software Development :: Testing :: Mocking
Classifier: Topic :: Software Development :: Testing :: Unit
Requires-Dist: openai (>=1.66,<2.0)
Requires-Dist: requests-toolbelt (>=1,<2)
Requires-Dist: respx (>=0.22.0,<0.23.0)
Project-URL: Documentation, https://mharrisb1.github.io/openai-responses-python/
Project-URL: Repository, https://github.com/mharrisb1/openai-responses-python
